exterminate/Alt29.py
exterminate/AltFloat.py
exterminate/AltList.py
exterminate/AltMath.py
exterminate/AltPrint.py
exterminate/AltRange.py
exterminate/AltSorting.py
exterminate/AltString.py
exterminate/Constants.py
exterminate/Gizoogle.py
exterminate/Utilities.py
exterminate/__init__.py
exterminate-0.3.1.dist-info/DESCRIPTION.rst
exterminate-0.3.1.dist-info/METADATA
exterminate-0.3.1.dist-info/RECORD
exterminate-0.3.1.dist-info/WHEEL
exterminate-0.3.1.dist-info/metadata.json
exterminate-0.3.1.dist-info/top_level.txt
