Metadata-Version: 2.0
Name: exterminate
Version: 0.3.1
Summary: Break Python programs with a simple import.
Home-page: https://github.com/adtac/exterminate
Author: Adhityaa Chandrasekar
Author-email: c.adhityaa@gmail.com
License: MIT
Platform: UNKNOWN
Classifier: Programming Language :: Python :: 2
Classifier: Programming Language :: Python :: 2.6
Classifier: Programming Language :: Python :: 2.7
Classifier: Programming Language :: Python :: 3
Classifier: Programming Language :: Python :: 3.2
Classifier: Programming Language :: Python :: 3.3
Classifier: Programming Language :: Python :: 3.4
Classifier: Programming Language :: Python :: 3.5
Classifier: Programming Language :: Python :: 3.6
